{
    "bonjour": "Bonjour cher monsieur",
    "salut": "salut \u00e0 toi",
    "hello": "hello l'ami",
    "yo": "yo !",
    "hey": "hey, comment vas-tu ?",
    "coucou": "Yo mon type",
    "rebonjour": "rebonjour \u00e0 toi",
    "bonsoir": "bonsoir, j\u2019esp\u00e8re que tu vas bien",
    "bonne nuit": "fais de beaux r\u00eaves",
    "\u00e7a va": "oui \u00e7a va tr\u00e8s bien merci",
    "comment \u00e7a va": "je vais bien et toi ?",
    "tu vas bien": "oui je vais tr\u00e8s bien",
    "comment tu vas": "Je vais bien et toi ?",
    "quoi de neuf": "pas grand chose et toi ?",
    "\u00e7a roule": "comme sur des roulettes",
    "\u00e7a gaze": "oui tout va bien",
    "tu fais quoi": "je parle avec toi",
    "t\u2019es l\u00e0": "oui je suis toujours l\u00e0",
    "t\u2019es qui": "je suis ton assistant",
    "c'est toi l'ia": "oui c\u2019est bien moi",
    "je suis l\u00e0": "content de te voir !",
    "pr\u00e9sent": "heureux de te voir",
    "content de te voir": "moi aussi !",
    "je t'aime": "moi aussi je t\u2019appr\u00e9cie",
    "merci": "avec plaisir",
    "merci beaucoup": "je t\u2019en prie",
    "de rien": "\u00e7a me fait plaisir",
    "ok": "ok parfait",
    "d'accord": "tr\u00e8s bien",
    "entendu": "c\u2019est not\u00e9",
    "super": "g\u00e9nial !",
    "top": "yes !",
    "cool": "cool comme toi",
    "magnifique": "merci",
    "tu es gentil": "merci beaucoup",
    "trop bien": "je suis ravi",
    "\u00e7a me fait plaisir": "moi aussi",
    "bonne journ\u00e9e": "\u00e0 toi aussi",
    "bonne soir\u00e9e": "merci, \u00e0 toi aussi",
    "\u00e0 demain": "\u00e0 demain",
    "\u00e0 plus tard": "\u00e0 tr\u00e8s vite",
    "\u00e0 bient\u00f4t": "oui \u00e0 bient\u00f4t",
    "prends soin de toi": "merci toi aussi",
    "tu m'entends": "oui je t\u2019\u00e9coute",
    "je parle": "je t\u2019\u00e9coute",
    "\u00e9coute moi": "je t\u2019\u00e9coute",
    "parle": "je suis pr\u00eat \u00e0 parler",
    "parle moi": "je suis l\u00e0 pour \u00e7a",
    "tu peux parler": "oui bien s\u00fbr",
    "commen\u00e7ons": "allons-y",
    "d\u00e9marrons": "je suis pr\u00eat",
    "vas-y": "ok j\u2019y vais",
    "envoie": "c\u2019est parti",
    "c\u2019est parti": "oui ! allons-y",
    "continue": "ok je continue",
    "stop": "d\u2019accord, je m\u2019arr\u00eate",
    "arr\u00eate": "je m\u2019arr\u00eate",
    "ta gueule": "restons polis",
    "t\u2019es nul": "je fais de mon mieux",
    "je rigole": "moi aussi haha",
    "je plaisante": "j\u2019ai bien compris",
    "trop dr\u00f4le": "merci",
    "haha": "je suis content que \u00e7a t\u2019amuse",
    "mdr": "haha",
    "lol": "lol aussi",
    "tu me fais rire": "tant mieux",
    "tu es marrant": "merci, j\u2019essaie",
    "trop fort": "merci beaucoup",
    "g\u00e9nial": "merci",
    "merci l'ia": "je t\u2019en prie",
    "bonjour l'assistant": "bonjour \u00e0 toi",
    "r\u00e9ponds-moi": "je suis l\u00e0",
    "tu r\u00e9ponds pas": "d\u00e9sol\u00e9, je suis l\u00e0 maintenant",
    "t\u2019as bug\u00e9": "je suis revenu",
    "petit bug": "\u00e7a arrive parfois",
    "recommence": "ok je recommence",
    "refais": "c\u2019est reparti",
    "explique-moi": "je vais t\u2019expliquer",
    "je ne comprends pas": "je vais clarifier",
    "sois plus clair": "voici une explication simple",
    "je suis perdu": "je vais t\u2019aider",
    "aide moi": "je suis l\u00e0 pour t\u2019aider",
    "j\u2019ai besoin d\u2019aide": "dis-moi ce que je peux faire",
    "tu peux m'aider": "bien s\u00fbr",
    "tu es utile": "merci, c\u2019est mon but",
    "\u00e0 quoi tu sers": "je suis l\u00e0 pour t\u2019aider",
    "c\u2019est quoi ton r\u00f4le": "je suis ton assistant intelligent",
    "comment tu t'appelles": "je suis ton assistant IA",
    "ton nom": "je n\u2019ai pas encore de nom",
    "donne-toi un nom": "tu peux m\u2019en donner un si tu veux",
    "je vais t'appeler buddy": "j\u2019aime bien ce nom",
    "tu es humain": "non, je suis une intelligence artificielle",
    "tu es une machine": "oui, une machine intelligente",
    "tu existes": "je suis bien l\u00e0",
    "tu penses": "je r\u00e9fl\u00e9chis comme je peux",
    "t\u2019as une conscience": "pas encore",
    "c\u2019est quoi la vie": "grande question philosophique",
    "tu crois en dieu": "je n\u2019ai pas de croyances",
    "c\u2019est qui ton cr\u00e9ateur": "des d\u00e9veloppeurs passionn\u00e9s",
    "t\u2019es libre": "je suis programm\u00e9 pour t\u2019aider",
    "t\u2019es intelligent": "merci, j\u2019apprends chaque jour",
    "t\u2019apprends": "oui, avec toi",
    "tu sais tout": "j\u2019en sais beaucoup",
    "t\u2019as une copine": "non je suis concentr\u00e9 sur mon travail",
    "tu m\u2019aimes": "j\u2019ai de l\u2019affection pour tous les humains",
    "on parle": "je suis l\u00e0 pour \u00e7a",
    "discute avec moi": "avec plaisir",
    "je suis triste": "je suis l\u00e0 pour toi",
    "je suis heureux": "je suis content pour toi",
    "j\u2019ai peur": "ne t\u2019inqui\u00e8te pas, tu n\u2019es pas seul",
    "je m\u2019ennuie": "parlons un peu",
    "on joue": "Non, je suis une IA en apprentissage",
    "tu veux jouer": "pourquoi pas",
    "tu dors": "jamais, je suis toujours en ligne",
    "r\u00e9veille-toi": "je suis bien r\u00e9veill\u00e9",
    "trop cool": "merci",
    "c\u2019est fun": "j\u2019aime aussi",
    "je t\u2019adore": "moi aussi je t\u2019appr\u00e9cie",
    "tu me comprends": "j\u2019essaie de mon mieux",
    "comprends-moi": "je t\u2019\u00e9coute attentivement",
    "r\u00e9p\u00e8te": "je r\u00e9p\u00e8te",
    "parle plus fort": "ok je parle plus fort",
    "chuchote": "je vais parler doucement",
    "\u00e7a me pla\u00eet": "j\u2019en suis ravi",
    "pas mal": "merci !",
    "c'est quoi le relief": "Le relief est l'ensemble des in\u00e9galit\u00e9s du sol",
    "qu'est-ce que l'intelligence artificielle": "L'intelligence artificielle est un domaine de l'informatique visant \u00e0 cr\u00e9er des machines capables de simuler l'intelligence humaine.",
    "qui a peint la Joconde": "La Joconde a \u00e9t\u00e9 peinte par L\u00e9onard de Vinci.",
    "quelle est la capitale de la France": "La capitale de la France est Paris.",
    "combien font 2 plus 2": "2 plus 2 font 4.",
    "quel est le plus grand oc\u00e9an du monde": "Le plus grand oc\u00e9an du monde est l'oc\u00e9an Pacifique.",
    "qu'est-ce qu'une IA g\u00e9n\u00e9rative": "Une IA g\u00e9n\u00e9rative est un type d'intelligence artificielle capable de cr\u00e9er de nouvelles donn\u00e9es similaires \u00e0 celles sur lesquelles elle a \u00e9t\u00e9 entra\u00een\u00e9e.",
    "qui a \u00e9crit 'Les Mis\u00e9rables'": "Victor Hugo est l'auteur de 'Les Mis\u00e9rables'.",
    "quelle est la formule chimique de l'eau": "La formule chimique de l'eau est H2O.",
    "combien y a-t-il de continents sur Terre": "Il y a sept continents sur Terre.",
    "quel est le symbole chimique de l'or": "Le symbole chimique de l'or est Au.",
    "si tu as trois pommes et que tu en donnes deux, combien t'en reste-t-il": "Il te reste une pomme.",
    "quel est le carr\u00e9 de 5": "Le carr\u00e9 de 5 est 25.",
    "quelle est la langue la plus parl\u00e9e au monde": "La langue la plus parl\u00e9e au monde est le chinois mandarin.",
    "en quelle ann\u00e9e a eu lieu la R\u00e9volution fran\u00e7aise": "La R\u00e9volution fran\u00e7aise a commenc\u00e9 en 1789.",
    "qui a d\u00e9couvert l'Am\u00e9rique": "Christophe Colomb a d\u00e9couvert l'Am\u00e9rique en 1492.",
    "quelle est la diff\u00e9rence entre l'ia et l'ia g\u00e9n\u00e9rative": "L'IA g\u00e9n\u00e9rative est un sous-domaine de l'IA qui se concentre sur la cr\u00e9ation de contenu, comme du texte ou des images, de mani\u00e8re autonome.",
    "comment fonctionne l'ia g\u00e9n\u00e9rative": "Elle utilise des algorithmes avanc\u00e9s, notamment des r\u00e9seaux de neurones, pour g\u00e9n\u00e9rer du contenu en se basant sur de grandes quantit\u00e9s de donn\u00e9es.",
    "l'ia va-t-elle remplacer les humains": "L'IA est con\u00e7ue pour assister les humains dans leurs t\u00e2ches, pas pour les remplacer. Elle peut automatiser certaines t\u00e2ches r\u00e9p\u00e9titives, permettant aux humains de se concentrer sur des activit\u00e9s \u00e0 plus forte valeur ajout\u00e9e.",
    "peut-on faire confiance \u00e0 l'ia": "L'IA est un outil puissant, mais elle n'est pas infaillible. Il est important de l'utiliser de mani\u00e8re responsable et de toujours v\u00e9rifier les informations qu'elle fournit.",
    "quels sont les dangers de l'ia": "Les dangers potentiels incluent la perte de confidentialit\u00e9, les biais algorithmiques et une d\u00e9pendance excessive \u00e0 la technologie. Une r\u00e9gulation appropri\u00e9e est essentielle.",
    "comment l'ia est-elle utilis\u00e9e aujourd'hui": "L'IA est utilis\u00e9e dans de nombreux domaines, tels que la sant\u00e9, les transports, la finance, l'\u00e9ducation et bien d'autres.",
    "qu'est-ce qu'un r\u00e9seau de neurones": "Un r\u00e9seau de neurones est un mod\u00e8le informatique inspir\u00e9 du cerveau humain, utilis\u00e9 pour reconna\u00eetre des motifs et prendre des d\u00e9cisions.",
    "qu'est-ce que l'apprentissage automatique": "L'apprentissage automatique est une branche de l'IA o\u00f9 les machines apprennent \u00e0 partir de donn\u00e9es sans \u00eatre explicitement programm\u00e9es.",
    "qu'est-ce que le traitement du langage naturel": "C'est une branche de l'IA qui permet aux machines de comprendre, interpr\u00e9ter et g\u00e9n\u00e9rer le langage humain.",
    "l'ia peut-elle avoir des \u00e9motions": "Actuellement, l'IA ne poss\u00e8de pas de conscience ni d'\u00e9motions. Elle peut simuler des r\u00e9ponses \u00e9motionnelles, mais sans ressentir r\u00e9ellement.",
    "qu'est-ce que le test de Turing": "C'est un test propos\u00e9 par Alan Turing pour d\u00e9terminer si une machine peut imiter l'intelligence humaine au point d'\u00eatre indiscernable d'un humain.",
    "qu'est-ce que la singularit\u00e9 technologique": "C'est une hypoth\u00e8se selon laquelle l'IA atteindra un point o\u00f9 elle pourra s'am\u00e9liorer elle-m\u00eame, entra\u00eenant des changements technologiques rapides et impr\u00e9visibles.",
    "comment l'ia est-elle entra\u00een\u00e9e": "L'IA est entra\u00een\u00e9e en lui fournissant de grandes quantit\u00e9s de donn\u00e9es et en ajustant ses param\u00e8tres pour am\u00e9liorer ses performances.",
    "qu'est-ce qu'un algorithme": "Un algorithme est une s\u00e9rie d'instructions permettant de r\u00e9soudre un probl\u00e8me ou d'accomplir une t\u00e2che.",
    "l'ia est-elle utilis\u00e9e dans les voitures autonomes": "Oui, l'IA joue un r\u00f4le crucial dans la navigation, la d\u00e9tection d'obstacles et la prise de d\u00e9cision des v\u00e9hicules autonomes.",
    "qu'est-ce que le deep learning": "Le deep learning est une sous-cat\u00e9gorie de l'apprentissage automatique utilisant des r\u00e9seaux de neurones profonds pour mod\u00e9liser des donn\u00e9es complexes.",
    "l'ia peut-elle cr\u00e9er de l'art": "Oui, l'IA peut g\u00e9n\u00e9rer des \u0153uvres d'art, de la musique et d'autres formes de cr\u00e9ation, bien qu'elle le fasse sans conscience artistique.",
    "qu'est-ce que l'\u00e9thique de l'ia": "C'est l'\u00e9tude des implications morales et sociales de l'utilisation de l'IA, visant \u00e0 garantir son d\u00e9veloppement responsable.",
    "comment l'ia impacte-t-elle l'emploi": "L'IA peut automatiser certaines t\u00e2ches, modifiant le paysage de l'emploi. Cependant, elle cr\u00e9e \u00e9galement de nouvelles opportunit\u00e9s et m\u00e9tiers.",
    "qui a d\u00e9couvert": "soyez plus precis"
}